openapi_client/__init__.py
openapi_client/api_client.py
openapi_client/api_response.py
openapi_client/configuration.py
openapi_client/exceptions.py
openapi_client/rest.py
openapi_client/api/__init__.py
openapi_client/api/api_api.py
openapi_client/api/capabilities_api.py
openapi_client/api/conformance_api.py
openapi_client/api/conformance_declaration_api.py
openapi_client/api/copy2_dru_api.py
openapi_client/api/dru_api.py
openapi_client/api/get_capabilities_api.py
openapi_client/api/home_api.py
openapi_client/api/jobs_api.py
openapi_client/api/landing_page_api.py
openapi_client/api/process_description_api.py
openapi_client/api/processes_api.py
openapi_client/models/OneOfstringnumberintegerobjectarraybooleanfilemap.py
openapi_client/models/__init__.py
openapi_client/models/additional_parameter.py
openapi_client/models/additional_parameter_value_inner.py
openapi_client/models/bbox_processes.py
openapi_client/models/bbox_processes_crs.py
openapi_client/models/collection_info.py
openapi_client/models/collection_info_data_type.py
openapi_client/models/collections.py
openapi_client/models/conf_classes.py
openapi_client/models/copy2_additional_parameter.py
openapi_client/models/copy2_input_description.py
openapi_client/models/copy2_model_schema.py
openapi_client/models/copy2_ogcapppkg.py
openapi_client/models/copy2_ogcapppkg_execution_unit.py
openapi_client/models/copy2_output_description.py
openapi_client/models/copy2_process.py
openapi_client/models/copy2_schema_one_of.py
openapi_client/models/copy2_schema_one_of_all_of_inner.py
openapi_client/models/copy2_schema_one_of_inner.py
openapi_client/models/copy2_schema_one_of_inner_all_of_inner.py
openapi_client/models/crs.py
openapi_client/models/crs_one_of.py
openapi_client/models/crs_one_of_one_of.py
openapi_client/models/data_type.py
openapi_client/models/description_type.py
openapi_client/models/description_type_additional_parameters.py
openapi_client/models/description_type_additional_parameters_all_of.py
gmu_hpgc_api-0.1.0.dist-info/METADATA
gmu_hpgc_api-0.1.0.dist-info/WHEEL
gmu_hpgc_api-0.1.0.dist-info/top_level.txt
gmu_hpgc_api-0.1.0.dist-info/RECORD
