Metadata-Version: 2.1
Name: gmu-hpgc-api
Version: 0.1.0
Summary: HPGC API based on OGC API - Processes
Home-page: UNKNOWN
Author: Eugene Yu
Author-email: gyu@gmu.edu
License: MIT License
Keywords: OpenAPI,OpenAPI-Generator,OGC API - Processes,HPC,HPGC
Platform: UNKNOWN
Requires-Dist: aenum
Requires-Dist: pydantic <2,>=1.10.5
Requires-Dist: python-dateutil
Requires-Dist: urllib3 >=1.25.3
